can_sniffer/__init__.py
can_sniffer/__version__.py
can_sniffer/can_sniffer.py
can_sniffer/context.py
can_sniffer-0.0.8.dist-info/LICENSE.txt
can_sniffer-0.0.8.dist-info/METADATA
can_sniffer-0.0.8.dist-info/WHEEL
can_sniffer-0.0.8.dist-info/top_level.txt
can_sniffer-0.0.8.dist-info/RECORD
