Metadata-Version: 2.1
Name: can-sniffer
Version: 0.0.8
Summary: Sniffer to send and receive can messages running in an independant thread.
Author-email: Roberto Aldea <r.aldea.csic+pypi@gmail.com>, Marius Crisan <mariuscrsn+pypi@gmail.com>, Pablo Pastor <pastorpflores+pypi@gmail.com>, Javier Sanz <javiersanzmoline@gmail.com>, Luis Roche <luis.roche@hotmail.com>
License: GNU GENERAL PUBLIC LICENSE
Project-URL: Homepage, https://github.com/WattRex/Battery-Cycler-Drivers
Project-URL: Bug Reports, https://github.com/WattRex/Battery-Cycler-Drivers/issues
Project-URL: Bug Tracker, https://github.com/WattRex/Battery-Cycler-Drivers/issues
Project-URL: Source, https://github.com/WattRex/Battery-Cycler-Drivers/tree/develop/code/drv_can
Project-URL: Funding, https://donate.pypi.org
Keywords: CANBus,Embedded Systems,Sniffer
Classifier: Development Status :: 3 - Alpha
Classifier: Topic :: Software Development :: Embedded Systems
Classifier: Operating System :: OS Independent
Classifier: License :: OSI Approved :: GNU Affero General Public License v3
Classifier: Programming Language :: Python :: 3
Classifier: Programming Language :: Python :: 3.7
Classifier: Programming Language :: Python :: 3.8
Classifier: Programming Language :: Python :: 3.9
Classifier: Programming Language :: Python :: 3.10
Classifier: Programming Language :: Python :: 3 :: Only
Requires-Python: >=3.7
License-File: LICENSE.txt
Requires-Dist: python-can >=4.2.2
Requires-Dist: system-config-tool >=0.0.6
Requires-Dist: system-logger-tool >=0.0.3
Requires-Dist: system-shared-tool >=0.2.5
